determine_slice_assignment_action.py
determine_slice_assignment_action-0.1.0a6.dist-info/licenses/LICENSE
determine_slice_assignment_action-0.1.0a6.dist-info/METADATA
determine_slice_assignment_action-0.1.0a6.dist-info/WHEEL
determine_slice_assignment_action-0.1.0a6.dist-info/top_level.txt
determine_slice_assignment_action-0.1.0a6.dist-info/RECORD
