Metadata-Version: 2.4
Name: determine-slice-assignment-action
Version: 0.1.0a6
Summary: This function determines what action should be taken when performing slice assignment on a sequence.
Author-email: Jifeng Wu <jifengwu2k@gmail.com>
License-Expression: MIT
Project-URL: Homepage, https://github.com/jifengwu2k/determine-slice-assignment-action
Project-URL: Bug Tracker, https://github.com/jifengwu2k/determine-slice-assignment-action/issues
Classifier: Programming Language :: Python :: 2
Classifier: Programming Language :: Python :: 3
Classifier: Operating System :: OS Independent
Requires-Python: >=2
License-File: LICENSE
Requires-Dist: canonical-interval
Requires-Dist: canonical-range
Dynamic: license-file
